dyhash/__init__.py
dyhash/attack_utils.py
dyhash/cli.py
dyhash/hash_utils.py
dyhash/report_utils.py
dyhash/strength_utils.py
dyhash_v2-0.1.1.dist-info/METADATA
dyhash_v2-0.1.1.dist-info/WHEEL
dyhash_v2-0.1.1.dist-info/entry_points.txt
dyhash_v2-0.1.1.dist-info/top_level.txt
dyhash_v2-0.1.1.dist-info/RECORD
