Metadata-Version: 2.4
Name: dyhash-v2
Version: 0.1.1
Summary: Advanced password analysis and hashing suite
Author: Hady Hassan
Requires-Python: >=3.8
Requires-Dist: bcrypt
Requires-Dist: argon2-cffi
Dynamic: author
Dynamic: requires-dist
Dynamic: requires-python
Dynamic: summary
